{
  "swagger": "2.0",
  "info": {
    "version": "1.0.0",
    "title": "REST API",
    "description": ""
  },
  "host": "localhost:3000",
  "basePath": "/",
  "tags": [],
  "schemes": [
    "http"
  ],
  "consumes": [],
  "produces": [],
  "paths": {
    "/v1/products/": {
      "post": {
        "tags": [],
        "description": "",
        "parameters": [],
        "responses": {
          "201": {
            "description": "Created"
          },
          "404": {
            "description": "Not Found"
          }
        }
      }
    },
    "/v1/products/{id}": {
      "put": {
        "tags": [],
        "description": "",
        "parameters": [
          {
            "name": "id",
            "in": "path",
            "required": true,
            "type": "string"
          }
        ],
        "responses": {
          "200": {
            "description": "OK"
          },
          "404": {
            "description": "Not Found"
          }
        }
      },
      "get": {
        "tags": [],
        "description": "",
        "parameters": [
          {
            "name": "id",
            "in": "path",
            "required": true,
            "type": "string"
          }
        ],
        "responses": {
          "200": {
            "description": "OK"
          },
          "404": {
            "description": "Not Found"
          }
        }
      },
      "delete": {
        "tags": [],
        "description": "",
        "parameters": [
          {
            "name": "id",
            "in": "path",
            "required": true,
            "type": "string"
          }
        ],
        "responses": {
          "200": {
            "description": "OK"
          },
          "404": {
            "description": "Not Found"
          }
        }
      }
    }
  },
  "definitions": {}
}